indico_previewer_jupyter/__init__.py
indico_previewer_jupyter/blueprint.py
indico_previewer_jupyter/controllers.py
indico_previewer_jupyter/cpp_highlighter.py
indico_previewer_jupyter/plugin.py
indico_previewer_jupyter/static/dist/0108e89c9003e8c14ea3c4e99b09653e.woff
indico_previewer_jupyter/static/dist/02271ec5cb9f5b4588ac53d7efbe6de8.woff
indico_previewer_jupyter/static/dist/073b3402d036714b43709614d1da717a.woff
indico_previewer_jupyter/static/dist/0c3b8929d377c0e9b2f3a9c872e3337b.woff
indico_previewer_jupyter/static/dist/172d3529b26f8cedef6b5ddef7546e02.woff2
indico_previewer_jupyter/static/dist/20f389c4120be058d80a3cd6a2f5a9b9.woff2
indico_previewer_jupyter/static/dist/2960900c4f271311eb36d175a209aa0a.woff2
indico_previewer_jupyter/static/dist/2f7bc363fc5424ebda5903f74c404a99.ttf
indico_previewer_jupyter/static/dist/354501bac435c3264834b80301089bad.woff
indico_previewer_jupyter/static/dist/39890742bc957b368704509bb2f4163c.woff2
indico_previewer_jupyter/static/dist/3a99e70aee4076660d38b312c7cac2f9.woff
indico_previewer_jupyter/static/dist/3f07ed67f06c720120cedd0bad5f60e2.woff
indico_previewer_jupyter/static/dist/428978dc7837d46de0916f266f5a43df.woff
indico_previewer_jupyter/static/dist/4ad7c7e8bb8d10a34bb7c4bb567cef92.ttf
indico_previewer_jupyter/static/dist/4c6b94fd1d07f8beff7cf3364d4d4555.woff
indico_previewer_jupyter/static/dist/4c761b3711973ab04edf7ea6f1fbacdc.ttf
indico_previewer_jupyter/static/dist/4f35fbcc9ee8614c2bcc8c28314db234.woff
indico_previewer_jupyter/static/dist/57f5c1837853986ea1dbadbb8f4f6074.ttf
indico_previewer_jupyter/static/dist/5b49f4993ae22d7975b413caed1a4c01.ttf
indico_previewer_jupyter/static/dist/6d3d25f4820d0da8f01fa3d2c7cbb8c2.woff2
indico_previewer_jupyter/static/dist/6de7d4b539221a49e9e241b734653ecf.ttf
indico_previewer_jupyter/static/dist/6eec866c69313624be6061a5c86f0944.woff2
indico_previewer_jupyter/static/dist/6fdf0ac577be0ba82a4c9a89b8eef91b.woff
indico_previewer_jupyter/static/dist/73ea273a72f4aca30ca528cf9117470a.woff2
indico_plugin_previewer_jupyter-3.3.1.dist-info/METADATA
indico_plugin_previewer_jupyter-3.3.1.dist-info/WHEEL
indico_plugin_previewer_jupyter-3.3.1.dist-info/entry_points.txt
indico_plugin_previewer_jupyter-3.3.1.dist-info/RECORD
