Metadata-Version: 2.3
Name: indico-plugin-previewer-jupyter
Version: 3.3.1
Summary: Jupyter notebook rendering for attachments in Indico
Project-URL: GitHub, https://github.com/indico/indico-plugins
Author-email: Indico Team <indico-team@cern.ch>
License-Expression: MIT
Classifier: Environment :: Plugins
Classifier: Environment :: Web Environment
Classifier: License :: OSI Approved :: MIT License
Classifier: Programming Language :: Python :: 3.12
Requires-Python: <3.13,>=3.12.2
Requires-Dist: indico>=3.3
Requires-Dist: nbconvert<8,>=7.16.4
